glask
