Metadata-Version: 1.0
Name: Glask
Version: 0.0.22
Summary: An extension for flask applications with best practices.
Home-page: https://github.com/vamf12/Glask
Author: UNKNOWN
Author-email: UNKNOWN
License: BSD
Platform: UNKNOWN
